odoo9_addon_base_report_to_printer-9.0.2.1.1-py2.7-nspkg.pth
odoo_addons/base_report_to_printer/report_service.py
odoo_addons/base_report_to_printer/__openerp__.py
odoo_addons/base_report_to_printer/__init__.py
odoo_addons/base_report_to_printer/README.rst
odoo_addons/base_report_to_printer/security/security.xml
odoo_addons/base_report_to_printer/migrations/9.0.1.0.0/pre-migration.py
odoo_addons/base_report_to_printer/migrations/9.0.2.0.0/post-10-create_server_record.py
odoo_addons/base_report_to_printer/migrations/9.0.2.1.0/pre-migration.py
odoo_addons/base_report_to_printer/models/printing_job.py
odoo_addons/base_report_to_printer/models/printing_printer.py
odoo_addons/base_report_to_printer/models/report.py
odoo_addons/base_report_to_printer/models/printing_server.py
odoo_addons/base_report_to_printer/models/printing_report_xml_action.py
odoo_addons/base_report_to_printer/models/printing_action.py
odoo_addons/base_report_to_printer/models/__init__.py
odoo_addons/base_report_to_printer/models/ir_actions_report_xml.py
odoo_addons/base_report_to_printer/models/res_users.py
odoo_addons/base_report_to_printer/i18n/zh_CN.po
odoo_addons/base_report_to_printer/i18n/base_report_to_printer.pot
odoo_addons/base_report_to_printer/i18n/pt.po
odoo_addons/base_report_to_printer/i18n/it.po
odoo_addons/base_report_to_printer/i18n/es.po
odoo_addons/base_report_to_printer/i18n/tr.po
odoo_addons/base_report_to_printer/i18n/hr.po
odoo_addons/base_report_to_printer/i18n/bg.po
odoo_addons/base_report_to_printer/i18n/gl.po
odoo_addons/base_report_to_printer/i18n/ca.po
odoo_addons/base_report_to_printer/i18n/sl.po
odoo_addons/base_report_to_printer/i18n/es_ES.po
odoo_addons/base_report_to_printer/i18n/pt_PT.po
odoo_addons/base_report_to_printer/i18n/nl.po
odoo_addons/base_report_to_printer/i18n/am.po
odoo_addons/base_report_to_printer/i18n/de.po
odoo_addons/base_report_to_printer/i18n/fr.po
odoo_addons/base_report_to_printer/i18n/pt_BR.po
odoo9_addon_base_report_to_printer-9.0.2.1.1.dist-info/top_level.txt
odoo9_addon_base_report_to_printer-9.0.2.1.1.dist-info/WHEEL
odoo9_addon_base_report_to_printer-9.0.2.1.1.dist-info/RECORD
odoo9_addon_base_report_to_printer-9.0.2.1.1.dist-info/metadata.json
odoo9_addon_base_report_to_printer-9.0.2.1.1.dist-info/DESCRIPTION.rst
odoo9_addon_base_report_to_printer-9.0.2.1.1.dist-info/METADATA
odoo9_addon_base_report_to_printer-9.0.2.1.1.dist-info/namespace_packages.txt
