Metadata-Version: 2.0
Name: odoo9-addon-base-report-to-printer
Version: 9.0.2.1.1
Summary: Report to printer
Home-page: http://www.agilebg.com
Author: Agile Business Group & Domsense, Pegueroles SCP, NaN, LasLabs, Odoo Community Association (OCA)
Author-email: support@odoo-community.org
License: AGPL-3
Platform: UNKNOWN
Requires-Dist: odoo (<9.1a,>=9.0a)
Requires-Dist: pycups
Classifier: Programming Language :: Python :: 2.7
Classifier: Framework :: Odoo
Classifier: License :: OSI Approved :: GNU Affero General Public License v3
